cellarc/__init__.py
cellarc/_version.py
cellarc/data.py
cellarc/signatures.py
cellarc/solver.py
cellarc/utils.py
cellarc/eval/__init__.py
cellarc/eval/common.py
cellarc/generation/__init__.py
cellarc/generation/cax_runner.py
cellarc/generation/constants.py
cellarc/generation/dataset.py
cellarc/generation/fingerprints.py
cellarc/generation/helpers.py
cellarc/generation/metrics.py
cellarc/generation/morphology.py
cellarc/generation/reconstruction.py
cellarc/generation/rule_table.py
cellarc/generation/rules.py
cellarc/generation/sampling.py
cellarc/generation/serialization.py
cellarc/visualization/__init__.py
cellarc/visualization/ca_rollout_viz.py
cellarc/visualization/episode_cards.py
cellarc/visualization/episode_viz.py
cellarc/visualization/palette.py
cellarc/visualization/plot_signatures.py
cellarc-0.1.2.dist-info/METADATA
cellarc-0.1.2.dist-info/WHEEL
cellarc-0.1.2.dist-info/licenses/LICENSE
cellarc-0.1.2.dist-info/RECORD
