Metadata-Version: 2.4
Name: cellarc
Version: 0.1.2
Summary: Generation and manipulation of cellular automata datasets
Project-URL: Homepage, https://github.com/mireklzicar/cellarc
Project-URL: Repository, https://github.com/mireklzicar/cellarc
Project-URL: Issues, https://github.com/mireklzicar/cellarc/issues
Author-email: Miroslav Lzicar <mirek@mzl.ai>
License: Apache-2.0
License-File: LICENSE
Keywords: ARC,cellular automata,datasets,generative-ai,machine-learning
Classifier: Development Status :: 3 - Alpha
Classifier: Intended Audience :: Developers
Classifier: Intended Audience :: Science/Research
Classifier: License :: OSI Approved :: Apache Software License
Classifier: Programming Language :: Python :: 3.8
Classifier: Programming Language :: Python :: 3.9
Classifier: Programming Language :: Python :: 3.10
Classifier: Programming Language :: Python :: 3.11
Classifier: Programming Language :: Python :: 3.12
Classifier: Topic :: Games/Entertainment :: Simulation
Classifier: Topic :: Scientific/Engineering :: Artificial Intelligence
Requires-Python: >=3.8
Requires-Dist: datasets>=2.14
Requires-Dist: huggingface-hub>=0.18
Requires-Dist: matplotlib
Requires-Dist: numpy
Requires-Dist: pyarrow
Requires-Dist: tqdm
Provides-Extra: all
Requires-Dist: cax; (python_version >= '3.11') and extra == 'all'
Requires-Dist: flax; extra == 'all'
Requires-Dist: jax; extra == 'all'
Provides-Extra: dev
Requires-Dist: black; extra == 'dev'
Requires-Dist: bump2version; extra == 'dev'
Requires-Dist: cax; (python_version >= '3.11') and extra == 'dev'
Requires-Dist: flake8; extra == 'dev'
Requires-Dist: pytest; extra == 'dev'
